derep_genomes/__init__.py
derep_genomes/__main__.py
derep_genomes/_version.py
derep_genomes/dbops.py
derep_genomes/general.py
derep_genomes/graph.py
derep_genomes-1.0.3.dist-info/LICENSE
derep_genomes-1.0.3.dist-info/METADATA
derep_genomes-1.0.3.dist-info/WHEEL
derep_genomes-1.0.3.dist-info/entry_points.txt
derep_genomes-1.0.3.dist-info/top_level.txt
derep_genomes-1.0.3.dist-info/RECORD
