Metadata-Version: 2.1
Name: derep-genomes
Version: 1.0.3
Summary: A simple genome de-replication tool with fastANI
Home-page: https://github.com/genomewalker/derep-genomes
Author: Antonio Fernandez-Guerra
Author-email: antonio@metagenomics.eu
License: GNUv3
Keywords: derep-genomes
Platform: UNKNOWN
Classifier: Programming Language :: Python :: 3.7
Classifier: Programming Language :: Python :: 3.8
Classifier: Programming Language :: Python :: 3.9
License-File: LICENSE
Requires-Dist: pandas (>=1.1.2)
Requires-Dist: scipy (>=1.5.2)
Requires-Dist: networkx (>=2.5)
Requires-Dist: simple-slurm (>=0.2.2)
Requires-Dist: tqdm (>=4.62.2)
Requires-Dist: PyYAML (>=5.4)
Requires-Dist: leidenalg (>=0.8.2)
Requires-Dist: python-igraph (>=0.8.3)
Requires-Dist: biopython (>=1.78)
